llmscorecard/__init__.py
llmscorecard/model_withweights.py
llmscorecard-0.0.2.dist-info/licenses/LICENSE
llmscorecard-0.0.2.dist-info/METADATA
llmscorecard-0.0.2.dist-info/WHEEL
llmscorecard-0.0.2.dist-info/top_level.txt
llmscorecard-0.0.2.dist-info/RECORD
