Metadata-Version: 2.4
Name: llmscorecard
Version: 0.0.2
Summary: Regression-based LLM benchmark ratings + publication-ready scorecards.
Author: YOUR NAME
License-Expression: MIT
Project-URL: Homepage, https://github.com/jaeday1212/llmscorecard
Project-URL: Source, https://github.com/jaeday1212/llmscorecard
Project-URL: Issues, https://github.com/jaeday1212/llmscorecard/issues
Project-URL: Releases, https://github.com/jaeday1212/llmscorecard/releases
Keywords: llm,benchmark,evaluation,regression,leaderboard,report,stats,ai
Classifier: Development Status :: 2 - Pre-Alpha
Classifier: Intended Audience :: Developers
Classifier: Intended Audience :: Science/Research
Classifier: Operating System :: OS Independent
Classifier: Programming Language :: Python :: 3
Classifier: Programming Language :: Python :: 3 :: Only
Classifier: Programming Language :: Python :: 3.9
Classifier: Programming Language :: Python :: 3.10
Classifier: Programming Language :: Python :: 3.11
Classifier: Programming Language :: Python :: 3.12
Classifier: Topic :: Scientific/Engineering :: Artificial Intelligence
Requires-Python: >=3.9
License-File: LICENSE
Requires-Dist: numpy>=1.23
Requires-Dist: scikit-learn>=1.2
Provides-Extra: report
Requires-Dist: jinja2>=3.1; extra == "report"
Requires-Dist: plotly>=5.0; extra == "report"
Provides-Extra: stats
Requires-Dist: pandas>=2.0; extra == "stats"
Requires-Dist: statsmodels>=0.14; extra == "stats"
Provides-Extra: dev
Requires-Dist: pytest>=7; extra == "dev"
Requires-Dist: ruff>=0.5; extra == "dev"
Requires-Dist: build>=1.2; extra == "dev"
Requires-Dist: twine>=5; extra == "dev"
Dynamic: license-file
